aribot/__init__.py
aribot/ai.py
aribot/api_keys.py
aribot/client.py
aribot/cloud.py
aribot/compliance.py
aribot/dashboard.py
aribot/digital_twin.py
aribot/economics.py
aribot/exceptions.py
aribot/finops.py
aribot/http.py
aribot/marketplace.py
aribot/pipeline.py
aribot/redteam.py
aribot/remediation.py
aribot/sbom.py
aribot/threat_modeling.py
aribot-1.4.0.dist-info/METADATA
aribot-1.4.0.dist-info/WHEEL
aribot-1.4.0.dist-info/RECORD
