Metadata-Version: 2.4
Name: aribot
Version: 1.4.0
Summary: Aribot Security Platform SDK by Aristiun & Ayurak - Threat modeling, compliance, and cloud security APIs
Project-URL: Homepage, https://developers.aristiun.com
Project-URL: Documentation, https://developers.aristiun.com/docs/python-sdk
Project-URL: Repository, https://github.com/Aristiun/aribot-python
Author-email: Aristiun <sdk@aristiun.com>, Ayurak <sdk@ayurak.com>
License-Expression: MIT
Keywords: api,cloud-security,compliance,devsecops,security,threat-modeling
Classifier: Development Status :: 5 - Production/Stable
Classifier: Intended Audience :: Developers
Classifier: License :: OSI Approved :: MIT License
Classifier: Programming Language :: Python :: 3
Classifier: Programming Language :: Python :: 3.8
Classifier: Programming Language :: Python :: 3.9
Classifier: Programming Language :: Python :: 3.10
Classifier: Programming Language :: Python :: 3.11
Classifier: Programming Language :: Python :: 3.12
Classifier: Topic :: Security
Classifier: Topic :: Software Development :: Libraries :: Python Modules
Requires-Python: >=3.8
Requires-Dist: pydantic>=2.0.0
Requires-Dist: requests>=2.28.0
Provides-Extra: dev
Requires-Dist: pytest-asyncio>=0.21.0; extra == 'dev'
Requires-Dist: pytest>=7.0.0; extra == 'dev'
Requires-Dist: responses>=0.23.0; extra == 'dev'
